{
  "type": "crafting_shapeless",
  "group": "stained_glass",
  "ingredients": [
    {
      "item": "minecraft:cocoa_beans"
    },
    {
      "tag": "minecraft:stained_glass"
    },
    {
      "tag": "minecraft:stained_glass"
    },
    {
      "tag": "minecraft:stained_glass"
    },
    {
      "tag": "minecraft:stained_glass"
    },
    {
      "tag": "minecraft:stained_glass"
    },
    {
      "tag": "minecraft:stained_glass"
    },
    {
      "tag": "minecraft:stained_glass"
    },
    {
      "tag": "minecraft:stained_glass"
    }
  ],
  "result": {
    "item": "minecraft:brown_stained_glass",
    "count": 8
  }
}
